server_client_manager/__init__.py
server_client_manager/data.py
server_client_manager/file.py
serverclientmanager-0.0.14.2.dist-info/LICENCE
serverclientmanager-0.0.14.2.dist-info/METADATA
serverclientmanager-0.0.14.2.dist-info/WHEEL
serverclientmanager-0.0.14.2.dist-info/top_level.txt
serverclientmanager-0.0.14.2.dist-info/RECORD
