Metadata-Version: 2.1
Name: serverclientmanager
Version: 0.0.14.2
Summary: authenticate and send files to a server and back
Home-page: UNKNOWN
Author: Theo Tappe
Author-email: <tappetheo@gmail.com>
License: UNKNOWN
Keywords: python,sockets
Platform: UNKNOWN
Classifier: Development Status :: 1 - Planning
Classifier: Intended Audience :: Developers
Classifier: Programming Language :: Python :: 3
Classifier: Operating System :: Unix
Classifier: Operating System :: MacOS :: MacOS X
Classifier: Operating System :: Microsoft :: Windows
License-File: LICENCE
Requires-Dist: werkzeug
